datedetective/BiLSTMTagger.py
datedetective/DateDetective.py
datedetective/Encoding.py
datedetective/ModelHandler.py
datedetective/__init__.py
datedetective/model_Ms_Zoey_Fadel_MD_state_dict.pth
datedetective-1.1.dist-info/LICENSE
datedetective-1.1.dist-info/METADATA
datedetective-1.1.dist-info/WHEEL
datedetective-1.1.dist-info/top_level.txt
datedetective-1.1.dist-info/RECORD
