Metadata-Version: 2.1
Name: datedetective
Version: 1.1
Summary: Machine learning approach to identifying date formats
Home-page: https://github.com/RSalethorn/DateDetective
Author: Rob Salethorn
Author-email: rob@salethorn.com
License-File: LICENSE
